getorg/__init__.py
getorg/core.py
getorg/markercluster_output.py
getorg/orgevents.py
getorg/orgmap.py
getorg/test.py
getorg-0.3.1.dist-info/DESCRIPTION.rst
getorg-0.3.1.dist-info/METADATA
getorg-0.3.1.dist-info/RECORD
getorg-0.3.1.dist-info/WHEEL
getorg-0.3.1.dist-info/metadata.json
getorg-0.3.1.dist-info/top_level.txt
