Metadata-Version: 1.0
Name: getorg
Version: 0.3.1
Summary: Information and analytics about GitHub organizations
Home-page: http://github.com/getorg/getorg
Author: Stuart Geiger
Author-email: stuart@stuartgeiger.com
License: MIT
Platform: UNKNOWN
